closedai/__init__.py
closedai/cli_main.py
closedai/client.py
closedai/runtime.py
closedai/schema.py
closedai/server.py
closedai/pipelines/__init__.py
closedai/pipelines/pipeline_base.py
closedai/pipelines/pipeline_dummy.py
closedai/pipelines/pipeline_huggingface.py
closedai-0.0.3.dist-info/LICENSE
closedai-0.0.3.dist-info/METADATA
closedai-0.0.3.dist-info/WHEEL
closedai-0.0.3.dist-info/entry_points.txt
closedai-0.0.3.dist-info/top_level.txt
closedai-0.0.3.dist-info/RECORD
