Metadata-Version: 2.1
Name: closedai
Version: 0.0.3
Summary: ClosedAI is a drop-in replacement for OpenAI.
Home-page: https://github.com/nateraw/closedai
Author: Nathan Raw
Author-email: naterawdata@gmail.com
License: Apache
License-File: LICENSE
Requires-Dist: fastapi (>=0.63.0)
Requires-Dist: pydantic (>=1.8.1)
Requires-Dist: uvicorn[standard] (>=0.13.4)
Requires-Dist: openai
Requires-Dist: fire
Requires-Dist: packaging (>=20.0)
Provides-Extra: quality
Requires-Dist: black (~=23.1) ; extra == 'quality'
Requires-Dist: ruff (>=0.0.241) ; extra == 'quality'
